{
  "MainRules":[



    {
      "name": "MeMovementRight",
      "situation": "right",
      "direction": "east",
      "original": [
        {
          "token": "1",
          "values": {
            "moved": 0
          }
        },
        {
          "token": [
            "path",
            "mud"
          ],
          "values": {
            "moved": 0
          }
        }
      ],
      "result": [
        {
          "token": 1,
          "values": {
            "moved": 1
          }
        },
        {
          "token": "me",
          "values": {
            "moved": 1
          }
        }
      ]
    },
    { "name": "MeMovementLeft",
      "situation":"left",
      "direction":"west",
      "original":[{"token":"me", "values":{"moved":0}},{"token":["path","mud"], "values":{"moved":0}}],
      "result": [
        {
          "token": "ME",
          "values": {
            "moved": 1
          }
        },
        {
          "token": "me",
          "values": {
            "moved": 1
          }
        }
      ]
    },
    { "name": "MeMovementDown",
      "situation":"down",
      "direction":"south",
      "original":[{"token":"me", "values":{"moved":0}},{"token":["path","mud"], "values":{"moved":0}}],
      "result":[{"token":"path", "values":{"moved":1}},{"token":"me", "values":{"moved":1}}]
    },
    { "name": "MeMovementUp",
      "situation":"up",
      "direction":"north",
      "original":[{"token":"me", "values":{"moved":0}},{"token":["path","mud"], "values":{"moved":0}}],
      "result":[{"token":"path", "values":{"moved":1}},{"token":"me", "values":{"moved":1}}]
    },


    { "name": "MeDiggingRight",
      "situation":"metaright",
      "direction":"east",
      "original":[{"token":"me", "values":{"moved":0}},{"token":"mud", "values":{"moved":0}}],
      "result":[{"token":"me", "values":{"moved":1}},{"token":"path", "values":{"moved":1}}]
    },
    { "name": "MeDiggingLeft",
      "situation":"metaleft",
      "direction":"west",
      "original":[{"token":"me", "values":{"moved":0}},{"token":"mud", "values":{"moved":0}}],
      "result":[{"token":"me", "values":{"moved":1}},{"token":["path"], "values":{"moved":1}}]
    },
    { "name": "MeDiggingDown",
      "situation":"metadown",
      "direction":"south",
      "original":[{"token":"me", "values":{"moved":0}},{"token":"mud", "values":{"moved":0}}],
      "result":[{"token":"me", "values":{"moved":1}},{"token":"path", "values":{"moved":1}}]
    },
    { "name": "MeDiggingUp",
      "situation":"metaup",
      "direction":"north",
      "original":[{"token":"me", "values":{"moved":0}},{"token":"mud", "values":{"moved":0}}],
      "result":[{"token":"me", "values":{"moved":1}},{"token":"path", "values":{"moved":1}}]
    }
  ]
}


